fastlinkcheck/__init__.py
fastlinkcheck/_nbdev.py
fastlinkcheck/linkcheck.py
fastlinkcheck-0.0.28.dist-info/LICENSE
fastlinkcheck-0.0.28.dist-info/METADATA
fastlinkcheck-0.0.28.dist-info/WHEEL
fastlinkcheck-0.0.28.dist-info/entry_points.txt
fastlinkcheck-0.0.28.dist-info/top_level.txt
fastlinkcheck-0.0.28.dist-info/RECORD
