Metadata-Version: 2.1
Name: fastlinkcheck
Version: 0.0.28
Summary: A python library
Home-page: https://github.com/fastai/fastlinkcheck/tree/master/
Author: jph00
Author-email: hamelh@umich.edu
License: Apache Software License 2.0
Keywords: python
Platform: UNKNOWN
Classifier: Development Status :: 3 - Alpha
Classifier: Intended Audience :: Developers
Classifier: License :: OSI Approved :: Apache Software License
Classifier: Natural Language :: English
Classifier: Programming Language :: Python :: 3.6
Classifier: Programming Language :: Python :: 3.7
Classifier: Programming Language :: Python :: 3.8
Requires-Python: >=3.6
Requires-Dist: fastcore
